[
{
  "precision" : "float",
  "n_asteroids" : "2000",
  "n_steps" : "1000",
  "runtime (seconds)" : "0.00229694",
  "asteroid time steps per second" : "8.70725e+08",
  "simulated years per second" : "435.362",
  "error" : "0.00520442"
}
,
{
  "precision" : "double",
  "n_asteroids" : "2000",
  "n_steps" : "1000",
  "runtime (seconds)" : "0.00378512",
  "asteroid time steps per second" : "5.28385e+08",
  "simulated years per second" : "264.192",
  "error" : "0.00522802"
}
,
{
  "precision" : "float",
  "n_asteroids" : "3000",
  "n_steps" : "1000",
  "runtime (seconds)" : "0.00342522",
  "asteroid time steps per second" : "8.75856e+08",
  "simulated years per second" : "291.952",
  "error" : "0.00520442"
}
,
{
  "precision" : "double",
  "n_asteroids" : "3000",
  "n_steps" : "1000",
  "runtime (seconds)" : "0.00566447",
  "asteroid time steps per second" : "5.29617e+08",
  "simulated years per second" : "176.539",
  "error" : "0.00522802"
}
,
{
  "precision" : "float",
  "n_asteroids" : "4000",
  "n_steps" : "1000",
  "runtime (seconds)" : "0.00456427",
  "asteroid time steps per second" : "8.76372e+08",
  "simulated years per second" : "219.093",
  "error" : "0.0250581"
}
,
{
  "precision" : "double",
  "n_asteroids" : "4000",
  "n_steps" : "1000",
  "runtime (seconds)" : "0.00754609",
  "asteroid time steps per second" : "5.30076e+08",
  "simulated years per second" : "132.519",
  "error" : "0.0250265"
}
]
